<oai_dc:dc xmlns:oai_dc="http://www.openarchives.org/OAI/2.0/oai_dc/" xmlns:dc="http://purl.org/dc/elements/1.1/" xmlns:xsi="http://www.w3.org/2001/XMLSchema-instance" xsi:schemaLocation="http://www.openarchives.org/OAI/2.0/oai_dc/ http://www.openarchives.org/OAI/2.0/oai_dc.xsd"><identifier>ir-10054-6318</identifier><datestamp>2012-03-20T07:09:19Z</datestamp><dc:title>A GENERALIZED TIME-DEPENDENT PSEUDOPOTENTIAL</dc:title><dc:creator>DATTA, SN</dc:creator><dc:creator>PRIYADARSHY, S</dc:creator><dc:publisher>ELSEVIER SCIENCE BV</dc:publisher><dc:date>2011-07-22T18:27:30Z</dc:date><dc:date>2011-12-26T12:52:31Z</dc:date><dc:date>2011-12-27T05:38:28Z</dc:date><dc:date>2011-07-22T18:27:30Z</dc:date><dc:date>2011-12-26T12:52:31Z</dc:date><dc:date>2011-12-27T05:38:28Z</dc:date><dc:date>1987</dc:date><dc:type>Article</dc:type><dc:identifier>CHEMICAL PHYSICS LETTERS, 135(1-2), 147-148</dc:identifier><dc:identifier>0009-2614</dc:identifier><dc:identifier>http://dx.doi.org/10.1016/0009-2614(87)87233-0</dc:identifier><dc:identifier>http://dspace.library.iitb.ac.in/xmlui/handle/10054/6318</dc:identifier><dc:identifier>http://hdl.handle.net/10054/6318</dc:identifier><dc:language>en</dc:language></oai_dc:dc>