<oai_dc:dc xmlns:oai_dc="http://www.openarchives.org/OAI/2.0/oai_dc/" xmlns:dc="http://purl.org/dc/elements/1.1/" xmlns:xsi="http://www.w3.org/2001/XMLSchema-instance" xsi:schemaLocation="http://www.openarchives.org/OAI/2.0/oai_dc/ http://www.openarchives.org/OAI/2.0/oai_dc.xsd"><identifier>ir-10054-7363</identifier><datestamp>2011-12-27T05:49:30Z</datestamp><dc:title>Identification of flow instabilities in the processing maps of AISI 304 stainless steel</dc:title><dc:creator>MURTY, SVSN</dc:creator><dc:creator>RAO, BN</dc:creator><dc:creator>KASHYAP, BP</dc:creator><dc:subject>dynamic material behavior</dc:subject><dc:subject>hot-working</dc:subject><dc:subject>flow instabilities</dc:subject><dc:subject>processing maps</dc:subject><dc:subject>aisi 304</dc:subject><dc:description>Among the various existing instability theories, a simple instability condition based on the Ziegler's continuum principles as applied to large plastic flow, is found to be more appropriate for delineating the regions of unstable metal flow during hot deformation. It can be used to any flow stress versus strain rate curve. This criterion has been validated using the flow stress data of AISI 304 stainless steel with microstructural observations. (c) 2004</dc:description><dc:publisher>ELSEVIER SCIENCE SA</dc:publisher><dc:date>2011-07-28T09:25:02Z</dc:date><dc:date>2011-12-26T12:58:51Z</dc:date><dc:date>2011-12-27T05:49:30Z</dc:date><dc:date>2011-07-28T09:25:02Z</dc:date><dc:date>2011-12-26T12:58:51Z</dc:date><dc:date>2011-12-27T05:49:30Z</dc:date><dc:date>2005</dc:date><dc:type>Article</dc:type><dc:identifier>JOURNAL OF MATERIALS PROCESSING TECHNOLOGY, 166(2), 268-278</dc:identifier><dc:identifier>0924-0136</dc:identifier><dc:identifier>http://dx.doi.org/10.1016/j.jmatprotec.2004.09.089</dc:identifier><dc:identifier>http://dspace.library.iitb.ac.in/xmlui/handle/10054/7363</dc:identifier><dc:identifier>http://hdl.handle.net/10054/7363</dc:identifier><dc:language>en</dc:language></oai_dc:dc>