<oai_dc:dc xmlns:oai_dc="http://www.openarchives.org/OAI/2.0/oai_dc/" xmlns:dc="http://purl.org/dc/elements/1.1/" xmlns:xsi="http://www.w3.org/2001/XMLSchema-instance" xsi:schemaLocation="http://www.openarchives.org/OAI/2.0/oai_dc/ http://www.openarchives.org/OAI/2.0/oai_dc.xsd"><identifier>ir-10054-9869</identifier><datestamp>2012-03-07T08:41:14Z</datestamp><dc:title>CASTE ASSOCIATIONS IN URBAN INDIA</dc:title><dc:creator>PUNEKAR, VB</dc:creator><dc:creator>HARIBABU, E</dc:creator><dc:publisher>MAN INDIA PUB</dc:publisher><dc:date>2011-08-17T12:38:05Z</dc:date><dc:date>2011-12-26T12:55:32Z</dc:date><dc:date>2011-12-27T05:41:04Z</dc:date><dc:date>2011-08-17T12:38:05Z</dc:date><dc:date>2011-12-26T12:55:32Z</dc:date><dc:date>2011-12-27T05:41:04Z</dc:date><dc:date>1980</dc:date><dc:type>Article</dc:type><dc:identifier>MAN IN INDIA, 60(1-2), 72-82</dc:identifier><dc:identifier>0025-1569</dc:identifier><dc:identifier>http://dspace.library.iitb.ac.in/xmlui/handle/10054/9869</dc:identifier><dc:identifier>http://hdl.handle.net/10054/9869</dc:identifier><dc:language>en</dc:language></oai_dc:dc>