<oai_dc:dc xmlns:oai_dc="http://www.openarchives.org/OAI/2.0/oai_dc/" xmlns:dc="http://purl.org/dc/elements/1.1/" xmlns:xsi="http://www.w3.org/2001/XMLSchema-instance" xsi:schemaLocation="http://www.openarchives.org/OAI/2.0/oai_dc/ http://www.openarchives.org/OAI/2.0/oai_dc.xsd"><identifier>ir-100-18186</identifier><datestamp>2016-01-15T08:40:07Z</datestamp><dc:title>Wigner distributions for gluons in a light-front dressed quark model</dc:title><dc:creator>MUKHERJEE, A</dc:creator><dc:creator>NAIR, S</dc:creator><dc:creator>OJHA, VK</dc:creator><dc:subject>VIRTUAL COMPTON-SCATTERING</dc:subject><dc:subject>ORBITAL ANGULAR-MOMENTUM</dc:subject><dc:subject>NUCLEON</dc:subject><dc:subject>SPIN</dc:subject><dc:subject>QCD</dc:subject><dc:description>We present a calculation of Wigner distributions for gluons in a light-front dressed quark model. We calculate the kinetic and canonical gluon orbital angular momentum and spin-orbit correlation of the gluons in this model.</dc:description><dc:publisher>AMER PHYSICAL SOC</dc:publisher><dc:date>2016-01-15T08:40:07Z</dc:date><dc:date>2016-01-15T08:40:07Z</dc:date><dc:date>2015</dc:date><dc:type>Article</dc:type><dc:identifier>PHYSICAL REVIEW D, 91(5)</dc:identifier><dc:identifier>1550-7998</dc:identifier><dc:identifier>1550-2368</dc:identifier><dc:identifier>http://dx.doi.org/10.1103/PhysRevD.91.054018</dc:identifier><dc:identifier>http://dspace.library.iitb.ac.in/jspui/handle/100/18186</dc:identifier><dc:language>en</dc:language></oai_dc:dc>