<oai_dc:dc xmlns:oai_dc="http://www.openarchives.org/OAI/2.0/oai_dc/" xmlns:dc="http://purl.org/dc/elements/1.1/" xmlns:xsi="http://www.w3.org/2001/XMLSchema-instance" xsi:schemaLocation="http://www.openarchives.org/OAI/2.0/oai_dc/ http://www.openarchives.org/OAI/2.0/oai_dc.xsd"><identifier>ir-100-15867</identifier><datestamp>2014-10-16T15:10:01Z</datestamp><dc:title>Mixed finite element methods for a fourth order reaction diffusion equation</dc:title><dc:creator>DANUMJAYA, P</dc:creator><dc:creator>PANI, AK</dc:creator><dc:subject>fourth order reaction diffusion equations</dc:subject><dc:subject>fisher Kolmogorov equation</dc:subject><dc:subject>mixed fem</dc:subject><dc:subject>a prior error estimates</dc:subject><dc:subject>completely discrete scheme</dc:subject><dc:subject>existence and uniqueness of the discrete problem</dc:subject><dc:subject>Lyapunov functional</dc:subject><dc:subject>Gronwall's Lemma</dc:subject><dc:subject>numerical experiment</dc:subject><dc:subject>SPLINE COLLOCATION METHODS</dc:subject><dc:subject>VELOCITY SELECTION</dc:subject><dc:subject>MARGINAL STABILITY</dc:subject><dc:subject>FRONT PROPAGATION</dc:subject><dc:description>Mixed finite element methods are applied to a fourth order reaction diffusion equation with different types of boundary conditions. Some a priori bounds are established with the help of Lyapunov functional. The semidiscrete schemes are derived using C0-piecewise linear finite elements in spatial direction and error estimates are obtained. The semidiscrete problem is then discretized in the temporal direction using backward Euler method and the wellposedness of the completely discrete scheme is discussed. Finally, a priori error estimates are established. While deriving a priori error estimates, Gronwall's lemma is applied and the constants involved in the error bounds do not depend exponentially on \documentclass{article} \usepackage{amsmath, amsthm, amssymb, amsfonts}\pagestyle{empty}\begin{document}$\frac{1}{\gamma}$ \end{document}, where ? is a parameter appeared in the fourth order derivative. (c) 2011Wiley Periodicals, Inc. Numer Methods Partial Differential Eq, 2012</dc:description><dc:publisher>WILEY-BLACKWELL</dc:publisher><dc:date>2014-10-16T15:10:01Z</dc:date><dc:date>2014-10-16T15:10:01Z</dc:date><dc:date>2012</dc:date><dc:type>Article</dc:type><dc:identifier>NUMERICAL METHODS FOR PARTIAL DIFFERENTIAL EQUATIONS, 28(4)1227-1251</dc:identifier><dc:identifier>http://dx.doi.org/10.1002/num.20679</dc:identifier><dc:identifier>http://dspace.library.iitb.ac.in/jspui/handle/100/15867</dc:identifier><dc:language>en</dc:language></oai_dc:dc>