<oai_dc:dc xmlns:oai_dc="http://www.openarchives.org/OAI/2.0/oai_dc/" xmlns:dc="http://purl.org/dc/elements/1.1/" xmlns:xsi="http://www.w3.org/2001/XMLSchema-instance" xsi:schemaLocation="http://www.openarchives.org/OAI/2.0/oai_dc/ http://www.openarchives.org/OAI/2.0/oai_dc.xsd"><identifier>ir-10054-7312</identifier><datestamp>2011-12-27T05:47:40Z</datestamp><dc:title>Effect of cooling rate on transformation texture and variant selection during beta -&gt; alpha transformation in Ti-5Ta-1.8Nb alloy</dc:title><dc:creator>KARTHIKEYAN, T</dc:creator><dc:creator>DASGUPTA, A</dc:creator><dc:creator>KHATIRKAR, R</dc:creator><dc:creator>SAROJA, S</dc:creator><dc:creator>SAMAJDAR, I</dc:creator><dc:creator>VIJAYALAKSHMI, M</dc:creator><dc:subject>commercially pure titanium</dc:subject><dc:subject>phase-transformation</dc:subject><dc:subject>ti-6al-4v</dc:subject><dc:subject>sheet</dc:subject><dc:subject>components</dc:subject><dc:subject>evolution</dc:subject><dc:subject>model</dc:subject><dc:subject>titanium</dc:subject><dc:subject>texture</dc:subject><dc:subject>ebsd</dc:subject><dc:subject>x-ray diffraction</dc:subject><dc:subject>variant selection</dc:subject><dc:description>The evolution of texture in a cold rolled Ti-5Ta-1.8Nb alloy sheet, during the alpha -&gt; beta -&gt; alpha transformation has been studied using EBSD and XRD techniques, for different cooling rates. The sheet exhibited a basal plane type texture upon cold rolling, and a sharp '{1 1 -2 0}parallel to rolling plane' transformation texture was inherited after the heat treatment. The microtexture analysis of the lamellar alpha/beta structure, suggested that this transformation texture arises from the {1 1 1}&lt; 1 1 0 &gt; type of high temperature beta texture, obeying the Burgers orientation relationship. The strength of the transformation texture was found to sharply increase with decrease in cooling rates, denoting variant selection. Two types of parent beta orientations with [1 1 0] parallel to either rolling directions are possible, and among their alpha product variants, 3 of them are common, and can be preferentially formed at the prior-beta grain boundaries. The role of grain boundary-alpha in influencing variant selection and the transformation texture for different cooling rates is described in this paper. .</dc:description><dc:publisher>ELSEVIER SCIENCE SA</dc:publisher><dc:date>2011-07-27T19:48:55Z</dc:date><dc:date>2011-12-26T12:58:10Z</dc:date><dc:date>2011-12-27T05:47:40Z</dc:date><dc:date>2011-07-27T19:48:55Z</dc:date><dc:date>2011-12-26T12:58:10Z</dc:date><dc:date>2011-12-27T05:47:40Z</dc:date><dc:date>2010</dc:date><dc:type>Article</dc:type><dc:identifier>MATERIALS SCIENCE AND ENGINEERING A-STRUCTURAL MATERIALS PROPERTIES MICROSTRUCTURE AND PROCESSING, 528(2), 549-558</dc:identifier><dc:identifier>0921-5093</dc:identifier><dc:identifier>http://dx.doi.org/10.1016/j.msea.2010.09.055</dc:identifier><dc:identifier>http://dspace.library.iitb.ac.in/xmlui/handle/10054/7312</dc:identifier><dc:identifier>http://hdl.handle.net/10054/7312</dc:identifier><dc:language>en</dc:language></oai_dc:dc>