<oai_dc:dc xmlns:oai_dc="http://www.openarchives.org/OAI/2.0/oai_dc/" xmlns:dc="http://purl.org/dc/elements/1.1/" xmlns:xsi="http://www.w3.org/2001/XMLSchema-instance" xsi:schemaLocation="http://www.openarchives.org/OAI/2.0/oai_dc/ http://www.openarchives.org/OAI/2.0/oai_dc.xsd"><identifier>ir-100-1964</identifier><datestamp>2011-12-15T09:11:16Z</datestamp><dc:title>Practical locality-awareness for large scale information sharing</dc:title><dc:creator>ABRAHAM I</dc:creator><dc:creator>BADOLA, A</dc:creator><dc:creator>BICKSON, D</dc:creator><dc:creator>MALKHI, D</dc:creator><dc:creator>MALOO, S</dc:creator><dc:creator>RON, S</dc:creator><dc:description>Tulip is an overlay for routing, searching and publish-lookup information sharing. It offers a unique combination of the advantages of both structured and unstructured overlays, that does not co-exist in any previous solution. Tulip features locality awareness (stretch 2) and fault tolerance (nodes can route around failures). It supports under the same roof exact keyed-lookup, nearest, copy location, and global information search. Tulip has been deployed and its locality and fault tolerance properties verified over a real wide-area network.</dc:description><dc:publisher>SPRINGER-VERLAG BERLIN</dc:publisher><dc:date>2011-10-23T18:10:30Z</dc:date><dc:date>2011-12-15T09:11:16Z</dc:date><dc:date>2011-10-23T18:10:30Z</dc:date><dc:date>2011-12-15T09:11:16Z</dc:date><dc:date>2005</dc:date><dc:type>Article; Proceedings Paper</dc:type><dc:identifier>PEER-TO-PEER SYSTEMS IV,3640,173-181</dc:identifier><dc:identifier>3-540-29068-0</dc:identifier><dc:identifier>0302-9743</dc:identifier><dc:identifier>http://dspace.library.iitb.ac.in/xmlui/handle/10054/15197</dc:identifier><dc:identifier>http://hdl.handle.net/100/1964</dc:identifier><dc:source>4th International Workshop on Peer-to-Peer Systems,Ithaca, NY,FEB 24-25, 2005</dc:source><dc:language>English</dc:language></oai_dc:dc>