<oai_dc:dc xmlns:oai_dc="http://www.openarchives.org/OAI/2.0/oai_dc/" xmlns:dc="http://purl.org/dc/elements/1.1/" xmlns:xsi="http://www.w3.org/2001/XMLSchema-instance" xsi:schemaLocation="http://www.openarchives.org/OAI/2.0/oai_dc/ http://www.openarchives.org/OAI/2.0/oai_dc.xsd"><identifier>ir-100-2812</identifier><datestamp>2011-12-15T09:12:40Z</datestamp><dc:title>Low-cost RF spectrum analyser</dc:title><dc:creator>RAO, MS</dc:creator><dc:creator>GOVINDARAJAN, M</dc:creator><dc:creator>LAL, R</dc:creator><dc:publisher>I E E E</dc:publisher><dc:date>2011-10-27T13:23:56Z</dc:date><dc:date>2011-12-15T09:12:40Z</dc:date><dc:date>2011-10-27T13:23:56Z</dc:date><dc:date>2011-12-15T09:12:40Z</dc:date><dc:date>1996</dc:date><dc:type>Proceedings Paper</dc:type><dc:identifier>1996 IEEE INTERNATIONAL CONFERENCE ON PERSONAL WIRELESS COMMUNICATIONS, PROCEEDINGS &amp; EXHIBITION - FUTURE ACCESS,254-256</dc:identifier><dc:identifier>0-7803-3177-X</dc:identifier><dc:identifier>http://dspace.library.iitb.ac.in/xmlui/handle/10054/16310</dc:identifier><dc:identifier>http://hdl.handle.net/100/2812</dc:identifier><dc:source>1996 IEEE International Conference on Personal Wireless Communications,NEW DELHI, INDIA,FEB 19-21, 1996</dc:source><dc:language>English</dc:language></oai_dc:dc>