<oai_dc:dc xmlns:oai_dc="http://www.openarchives.org/OAI/2.0/oai_dc/" xmlns:dc="http://purl.org/dc/elements/1.1/" xmlns:xsi="http://www.w3.org/2001/XMLSchema-instance" xsi:schemaLocation="http://www.openarchives.org/OAI/2.0/oai_dc/ http://www.openarchives.org/OAI/2.0/oai_dc.xsd"><identifier>ir-10054-4971</identifier><datestamp>2011-12-27T05:36:41Z</datestamp><dc:title>Controlling grain boundary energy to make austenitic stainless steels resistant to intergranular stress corrosion cracking</dc:title><dc:creator>WASNIK, DN</dc:creator><dc:creator>KAIN, V</dc:creator><dc:creator>SAMAJDAR, I</dc:creator><dc:creator>VERLINDEN, B</dc:creator><dc:creator>DE, PK</dc:creator><dc:subject>character-distribution</dc:subject><dc:subject>sensitization</dc:subject><dc:subject>austenitic stainless steel</dc:subject><dc:subject>corrosion</dc:subject><dc:subject>deformation processing</dc:subject><dc:subject>grain boundaries</dc:subject><dc:subject>intergranular corrosion</dc:subject><dc:subject>intergranular stress corrosion cracking</dc:subject><dc:subject>sensitization stress corrosion cracking</dc:subject><dc:description>Intergranular corrosion and intergranular stress corrosion cracking are the two localized corrosion mechanisms that are of concern to the typical applications of austenitic stainless steels in industries. Until recently, the common understanding was that a higher frequency of random boundaries increases the susceptibility, caused by a sensitization heat treatment or by operating temperatures, of austenitic stainless steels to both intergranular corrosion and intergranular stress corrosion cracking. A recent study([1]) demonstrated that extreme randomization of grain boundaries leads to a considerable improvement of resistance to both sensitization and intergranular corrosion. This work is a continuation of Ref. I and relates the effects of grain boundary randomization to intergranular stress corrosion cracking: the results show a trend consistent with earlier observations on intergranular corrosion. It is shown that there is improvement in resistance to intergranular stress corrosion cracking with extreme randomization of grain boundaries.</dc:description><dc:publisher>ASM INTERNATIONAL</dc:publisher><dc:date>2011-07-18T15:41:18Z</dc:date><dc:date>2011-12-26T12:50:42Z</dc:date><dc:date>2011-12-27T05:36:41Z</dc:date><dc:date>2011-07-18T15:41:18Z</dc:date><dc:date>2011-12-26T12:50:42Z</dc:date><dc:date>2011-12-27T05:36:41Z</dc:date><dc:date>2003</dc:date><dc:type>Article</dc:type><dc:identifier>JOURNAL OF MATERIALS ENGINEERING AND PERFORMANCE, 12(4), 402-407</dc:identifier><dc:identifier>1059-9495</dc:identifier><dc:identifier>http://dx.doi.org/10.1361/105994903770342926</dc:identifier><dc:identifier>http://dspace.library.iitb.ac.in/xmlui/handle/10054/4971</dc:identifier><dc:identifier>http://hdl.handle.net/10054/4971</dc:identifier><dc:language>en</dc:language></oai_dc:dc>